<!DOCTYPE verb SYSTEM "verb.dtd">
<verb>
<id>DaH~aY</id>

<frameset cdef="" edef="to sacrifice" id="01" vncls="">
<role argnum="0" argrole="sacrificer (agent)" vncls="" vntheta=""/>
<frame>
<mapping>

<comment/>
</mapping>
<example>
<parse>استيقظنا في العالم العربي بعدما ضحى البوعزيزي بنفسه وهو يكافح من أجل لقمة العيش لأسرته</parse>

<arg f="" g="al-Buu Aziizii" n="0">البوعزيزي</arg>
<arg f="" g="himself" n="1">بنفسه</arg>
<comment/>
</example>

<comment/>
</frame>

<role argnum="1" argrole="sacrficed (patient) - a PP" vncls="" vntheta=""/>
<comment/>
</frameset>
<comment/>
</verb>
