<!DOCTYPE verb SYSTEM "verb.dtd">
<verb>
<id>dAras</id>

<frameset cdef="" edef="reading to someone" id="01" vncls="">
<role argnum="0" argrole="reader" vncls="" vntheta=""/>
<frame>
<mapping>

<comment/>
</mapping>
<example>
<parse>دارس * الكتاب مع شقيقه</parse>

<arg f="" g="NONE" n="0">-NONE- * ?</arg>
<arg f="" g="the book" n="2">الكتاب</arg>
<arg f="" g="with his brother" n="1">مع شقيقه</arg>
<comment/>
</example>

<comment/>
</frame>

<role argnum="1" argrole="listner" vncls="" vntheta=""/>
<role argnum="2" argrole="subject / book" vncls="" vntheta=""/>
<comment/>
</frameset>
<frameset cdef="" edef="commiting" id="02" vncls="">
<role argnum="0" argrole="agent" vncls="" vntheta=""/>
<frame>
<mapping>

<comment/>
</mapping>
<example>
<parse>دارس * الذنب</parse>

<arg f="" g="NONE" n="0">-NONE- * ?</arg>
<arg f="" g="the guilt" n="1">الذنب</arg>
<comment/>
</example>

<comment/>
</frame>

<role argnum="1" argrole="thing commited" vncls="" vntheta=""/>
<comment/>
</frameset>
<comment/>
</verb>
