<!DOCTYPE verb SYSTEM "verb.dtd">
<verb>
    <id>das~-u</id>
    <frameset cdef="" edef="to put, slip into, insert" id="01">
        <role argnum="0" argrole="entity putting"/>
        <role argnum="1" argrole="thing being put"/>
        <role argnum="2" argrole="place"/>
        <frame>
            <example>
                <parse>
                    (PP
                    (PREP م)
                    (SBAR-NOM
                    (WHNP-6
                    (REL_PRON ما))
                    (S
                    (VP
                    (IV3MS+IV+IVSUFF_MOOD:I يشير)
                    (NP-SBJ
                    (-NONE- *T*-6))
                    (PP-CLR
                    (PREP الى)
                    (SBAR
                    (SUB_CONJ ان)
                    (S
                    (NP-TPC-7
                    (NOUN+CASE_INDEF_ACC احداً))
                    (VP
                    (PRT
                    (VERB_PART قد))
                    (IV3MS+IV+IVSUFF_MOOD:I يكون)
                    (VP
                    (PV+PVSUFF_SUBJ:3MS دس)
                    (NP-SBJ
                    (-NONE- *T*-7))
                    (NP-OBJ
                    (DET+NOUN+NSUFF_FEM_SG+CASE_DEF_ACC القنبلة))
                    (PP
                    (PREP في)
                    (NP
                    (NP
                    (DET+NOUN+NSUFF_FEM_SG+CASE_DEF_GEN الحقيبة))
                    (SBAR
                    (WHNP-8
                    (REL_PRON التي))
                    (S
                    (VP
                    (PV+PVSUFF_SUBJ:3FS فجرت)
                    (NP-SBJ
                    (-NONE- *T*-8))
                    (NP-OBJ
                    (DET+NOUN+NSUFF_FEM_SG+CASE_DEF_ACC الطائرة)))))))))))))))))))))))))))
                    (PUNC .))
                </parse>
                <arg f="" g="" n="0">-NONE- *T*-7</arg>
                <arg f="" g="the bomb" n="1">القنبلة</arg>
                <arg f="" g="in the suitcase that blew up the plane" n="2">في الحقيبة التي فجرت الطائرة</arg>
            </example>
        </frame>
    </frameset>
</verb>
