<!DOCTYPE verb SYSTEM "verb.dtd"><verb>
<id>faw~aq</id>

    <comment>EGYPTIAN ARABIC Framefile based on SaH~aY-v</comment>
<frameset cdef="" edef="to make someone to wake up" id="02" vncls="">
<role argnum="0" argrole="causer" vncls="" vntheta="" />
<frame>
<mapping>
<comment />
</mapping>
<example>
<parse>ابويا بيصحي * ني من النوم كل مرة أتاخر في النوم</parse>
<comment />
<arg f="" g="my father" n="0">ابويا</arg>
<arg f="" g="me" n="1">ني</arg>
<arg f="" g="from sleeping" n="2">من النوم</arg>
</example>
<comment />
</frame>
<comment>Based on roleset SaH~aY-v.02</comment>
<role argnum="1" argrole="entity waking up" vncls="" vntheta="" />
<role argnum="2" argrole="from" vncls="" vntheta="" />
</frameset>
</verb>