<!DOCTYPE verb SYSTEM "verb.dtd">
<verb>
<id>gadA-u</id>
<frameset cdef="" edef="to become" id="01" vncls="">
<role argnum="1" argrole="entity changing" vncls="" vntheta=""/>
<role argnum="2" argrole="new state" vncls="" vntheta=""/>
<frame>
<example>
<parse>(S
                                (VP
                                  (IV3MS+IV+IVSUFF_MOOD:I يتوقف)
                                  (NP-SBJ
                                    (DET+NOUN+CASE_DEF_NOM التوقيت))
                                  (ADVP
                                    (-NONE- *T*-1)))))
                            (CONJ و)
                            (SBAR
                              (WHADVP-3
                                (-NONE- 0))
                              (S
                                (VP
                                  (IV3MS+IV+IVSUFF_MOOD:I يغدو)
                                  (NP-SBJ
                                    (DET+NOUN+CASE_DEF_NOM الصراع))
                                  (PP-PRD
                                    (PREP ب)
                                    (NP
                                      (PRT
                                        (NEG_PART لا))
                                      (NOUN+CASE_INDEF_GEN حدود)))
                                  (NP-ADV
                                    (NOUN+CASE_DEF_ACC مع)
                                    (NP
                                      (PRON_3MP هم)))
                                  (ADVP
                                    (-NONE- *T*-3))))))))
                      (ADVP
                        (-NONE- *T*-7))))))))))))
  (PUNC ,)</parse>
<arg f="" g="struggele" n="1">الصراع</arg>
<arg f="" g="Without limits" n="2">بلا حدود</arg>

<comment/>
</example>
<example>
<parse>(S
  (S
    (CONJ و)
    (VP
      (IV3FS+IV+IVSUFF_MOOD:I تغدو)
      (NP-SBJ
        (NP
          (NOUN+CASE_DEF_NOM افلام)
          (NP
            (DET+NOUN+CASE_DEF_GEN الكرتون)))
        (ADJP
          (DET+ADJ+NSUFF_FEM_SG+CASE_DEF_NOM المسروقة)))
      (ADJP-PRD
        (ADJ+NSUFF_FEM_SG+CASE_INDEF_ACC شعبية)
        (NOUN+CASE_INDEF_ACC جداً))
      (PP-LOC
        (PREP في)
        (NP
          (DET+NOUN+CASE_DEF_GEN الغرب)))))
  (PUNC ,)</parse>
<arg f="" g="Carton films" n="0">افلام الكرتون</arg>
<arg f="" g="Public" n="1">شعبية</arg>
<arg f="tmp" g="in the western world" n="m">في الغرب</arg>

<comment/>
</example>

<comment/>
</frame>

<comment/>
</frameset>

<frameset cdef="" edef="to go or leave early in the morning" id="02" vncls="">
<role argnum="0" argrole="agent leaving early" vncls="" vntheta=""/>
<frame>
<mapping>

<comment/>
</mapping>
<example>
<parse>غدا الرجل الى عمله</parse>

<arg f="" g="the man" n="0">الرجل</arg>
<arg f="" g="to his work" n="1">الى عمله</arg>
<comment/>
</example>

<comment/>
</frame>

<role argnum="1" argrole="to what" vncls="" vntheta=""/>
<comment/>
</frameset>
<comment/>
</verb>
