<!DOCTYPE verb SYSTEM "verb.dtd">
<verb>
    <id>gA}iS</id>
    <comment/>
    <frameset cdef="" edef="diver / plunger / diving" id="01">
        <role argnum="0" argrole="diver / plunger / diving entity"/>
        <frame>
            <mapping>
                <comment/>
            </mapping>
            <example>
                <parse>(S
                    (VP
                    (PV+PVSUFF_SUBJ:3MS دخل)
                    (NP-SBJ-2
                    (-NONE- *))
                    (PP
                    (PREP الى)
                    (NP
                    (DET+NOUN+NSUFF_FEM_SG+CASE_DEF_GEN المرحلة)
                    (DET+ADJ+NSUFF_FEM_SG+CASE_DEF_GEN الاسلامية)
                    (DET+ADJ+NSUFF_FEM_SG+CASE_DEF_GEN المضيئة)))
                    (S-ADV
                    (S
                    (VP
                    (ADJ.VN+CASE_INDEF_ACC غائصاً)
                    (NP-SBJ
                    (-NONE- *-2))
                    (PP
                    (PREP على)
                    (NP
                    (DET+NOUN+CASE_DEF_GEN الحرف)
                    (DET+ADJ+CASE_DEF_GEN العربي)))))
                </parse>
                <comment/>
                <arg f="" g="he" n="0">-NONE- *-2</arg>
                <arg f="" g="on the Arabic letter" n="1">على الحرف العربي</arg>
            </example>
            <comment/>
        </frame>
        <comment/>
        <role argnum="1" argrole="location (marked by في)"/>
    </frameset>
</verb>
