<!DOCTYPE verb SYSTEM "verb.dtd">
<verb>
<id>Hal~-i</id>







<comment/>
<frameset cdef="" edef="to let go, or move away" id="07" vncls="">
<role argnum="0" argrole="entity moving away" vncls="" vntheta=""/>
<frame>
<mapping>
<comment/>
</mapping>
<example>
<parse>يا أخي حل * عننا بقى</parse>
<comment/>
<arg f="" g="my brother" n="0">* يا أخي</arg>
<arg f="" g="from us" n="1">عننا</arg>
</example>
<comment/>
</frame>
<comment>Egyptian</comment>
<role argnum="1" argrole="from what" vncls="" vntheta=""/>
</frameset>
</verb>
