<!DOCTYPE verb SYSTEM "verb.dtd">
<verb>
    <id>jamoE</id>
    <comment/>
    <frameset cdef="" edef="gathering, collecting, picking up" id="01">
        <role argnum="0" argrole="entity gathering"/>
        <frame>
            <mapping>
                <comment/>
            </mapping>
            <example>
                <parse>قام بجمع *  الاوراق من على الطاولة</parse>
                <comment/>
                <arg f="" g="NONE" n="0">-NONE- *?</arg>
                <arg f="" g="the papers" n="1">الاوراق</arg>
                <arg f="" g="from the top of the table" n="2">من على الطاولة</arg>
            </example>
            <comment/>
        </frame>
        <comment/>
        <role argnum="1" argrole="things gathered"/>
        <role argnum="2" argrole="from where"/>
    </frameset>
    <frameset cdef="" edef="addition, adding" id="02">
        <role argnum="0" argrole="entity adding things"/>
        <frame>
            <mapping>
                <comment/>
            </mapping>
            <example>
                <parse>قام بجمع *  الاعداد بدون استخدام الة حاسبة</parse>
                <comment/>
                <arg f="" g="NONE" n="0">-NONE- *?</arg>
                <arg f="" g="the numbers" n="1">الاعداد</arg>
            </example>
            <comment/>
        </frame>
        <comment/>
        <role argnum="1" argrole="things added"/>
        <role argnum="2" argrole="to what"/>
    </frameset>
</verb>
