<!DOCTYPE verb SYSTEM "verb.dtd">
<verb>
    <id>mumotali}</id>
    <frameset cdef="" edef="filled /  full of" id="01">
        <role argnum="1" argrole="filled /  full of thing"/>
        <role argnum="2" argrole="what?"/>
        <frame>
            <example>
                <parse>
                    (S
                    (CONJ و)
                    (PP
                    (PREP ب)
                    (NP
                    (NOUN+CASE_DEF_GEN قدر)
                    (SBAR
                    (SUB_CONJ ما)
                    (S
                    (VP
                    (PV+PVSUFF_SUBJ:3FS كانت)
                    (NP-SBJ
                    (NOUN_PROP زاهية)
                    (NOUN_PROP قدورة))
                    (ADJP-PRD
                    (ADJP
                    (ADJ+NSUFF_FEM_SG+CASE_INDEF_ACC ممتلئة)
                    (NP-ADV
                    (NOUN+CASE_INDEF_ACC حناناً)
                    (CONJ و)
                    (NOUN+CASE_INDEF_ACC حباً))
                    (PP
                    (PREP ل)
                    (NP
                    (NOUN+NSUFF_FEM_SG+CASE_DEF_GEN عائلت)
                    (NP
                    (POSS_PRON_3FS ها)))))
                    (PUNC ,)
                    (ADJP
                    (ADJ+NSUFF_FEM_SG+CASE_INDEF_ACC ملتصقة)
                    (PP
                    (PREP ب)
                    (NP
                    (NP
                    (NOUN_QUANT+CASE_DEF_GEN كل)
                    (NP
                    (NOUN+CASE_INDEF_GEN فرد)))
                    (PP
                    (PREP في)
                    (NP
                    (PRON_3FS ها))))))))))))
                    (PUNC ,)
                    (VP
                    (PV+PVSUFF_SUBJ:3MS كان)
                    (PP-PRD
                    (PREP ل)
                    (NP
                    (PRON_3FS ها)))
                    (ADVP
                    (ADV+CASE_INDEF_ACC أيضاً))
                    (NP-SBJ
                    (NP
                    (NP
                    (NP
                    (NOUN+NSUFF_FEM_SG+CASE_DEF_NOM عائلت)
                    (NP
                    (POSS_PRON_3FS ها)))
                    (ADJP
                    (DET+ADJ+NSUFF_FEM_SG+CASE_DEF_NOM الخاصة)))
                </parse>
                <arg f="" g="Zahia Qaddura" n="1">زاهية قدورة</arg>
                <arg f="" g="kindness" n="2">حناناً</arg>
            </example>
        </frame>
    </frameset>
</verb>
