<!DOCTYPE verb SYSTEM "verb.dtd">
<verb>
    <id>naHA-u</id>
    <frameset cdef="" edef="To blame" id="01">
        <role argnum="0" argrole="blamer"/>
        <role argnum="1" argrole="entity blamed"/>
        <role argnum="2" argrole="blamed for what?"/>
        <frame>
            <example>
                <parse>
                    (NP-SBJ-4
                    (NOUN_PROP شارون))
                    (PP
                    (PREP في)
                    (NP
                    (NP
                    (NP
                    (NOUN+CASE_DEF_GEN حرب)
                    (NP
                    (POSS_PRON_3MS ه)))
                    (ADJP
                    (DET+ADJ+NSUFF_FEM_SG+CASE_DEF_GEN الشرسة)))
                    (NP-ADV
                    (NOUN+CASE_DEF_ACC ضد)
                    (NP
                    (NP
                    (NOUN+NSUFF_FEM_SG+CASE_DEF_GEN مقاومة)
                    (NP
                    (DET+NOUN+CASE_DEF_GEN الشعب)
                    (DET+ADJ+CASE_DEF_GEN الفلسطيني)))
                    (ADJP
                    (DET+ADJ+NSUFF_FEM_SG+CASE_DEF_GEN الباسلة))))))
                    (S
                    (VP
                    (PRT
                    (NEG_PART ما))
                    (PV+PVSUFF_SUBJ:3MS زال)
                    (NP-SBJ
                    (-NONE- *-4))
                    (S
                    (VP
                    (IV3MS+IV+IVSUFF_MOOD:I ينحو)
                    (NP-SBJ
                    (-NONE- *-4))
                    (PP
                    (PREP ب)
                    (NP
                    (DET+NOUN+NSUFF_FEM_SG+CASE_DEF_GEN اللائمة)))
                    (PP-CLR
                    (PREP على)
                    (NP
                    (NP
                    (DET+NOUN+NSUFF_FEM_SG+CASE_DEF_GEN المقاومة)
                    (DET+ADJ+NSUFF_FEM_SG+CASE_DEF_GEN اللبنانية))
                </parse>
                <arg f="" g="He" n="0">-NONE- *-4&amp;lt;شارون</arg>
                <arg f="" g="Lebanese resistance" n="1">المقاومة اللبنانية</arg>
            </example>
        </frame>
    </frameset>
</verb>
