<!DOCTYPE verb SYSTEM "verb.dtd">
<verb>
    <id>OaHab~</id>
    <frameset cdef="" edef="to love" id="01">
        <role argnum="0" argrole="lover"/>
        <role argnum="1" argrole="loved"/>
        <frame>
            <example>
                <parse>
                    (VP
                    (PV+PVSUFF_SUBJ:3FS احبت)
                    (NP-SBJ
                    (-NONE- *))
                    (NP-OBJ
                    (NOUN_QUANT+CASE_DEF_ACC كل)
                    (SBAR-NOM
                    (WHNP-1
                    (REL_PRON الذين))
                    (S
                    (VP
                    (PV+PVSUFF_SUBJ:3MP كانوا)
                    (NP-SBJ
                    (-NONE- *T*-1))
                    (NP-PRD
                    (NOUN+CASE_DEF_ACC حول)
                    (NP
                    (PRON_3FS ها)))))))))
                </parse>
                <arg f="" g="She" n="0">-NONE- *</arg>
                <arg f="" g="all who were around her" n="1">كل الذين كانوا حولها</arg>
            </example>
        </frame>
    </frameset>
    <frameset cdef="" edef="To want or prefer" id="02">
        <role argnum="0" argrole="Wanter"/>
        <role argnum="1" argrole="thing wanted"/>
        <frame>
            <example>
                <parse>
                    (S
                    (VP
                    (IV1P+IV+IVSUFF_MOOD:I نحب)
                    (NP-SBJ
                    (-NONE- *))
                    (SBAR
                    (SUB_CONJ ان)
                    (S
                    (VP
                    (IV1P+IV+IVSUFF_MOOD:S نذكر)
                    (NP-SBJ
                    (-NONE- *))
                    (ADVP
                    (ADV هنا))
                    (PUNC ,)
                    (PP
                    (PREP على)
                    (NP
                    (NOUN+CASE_DEF_GEN سبيل)
                    (NP
                    (DET+NOUN+CASE_DEF_GEN المثال)
                    (CONJ لا)
                    (DET+NOUN+CASE_DEF_GEN الحصر))))
                    (PUNC ,)
                    (PP-CLR
                    (PREP ب)
                    (SBAR
                    (SUB_CONJ ان)
                    (S
                    (NP-TPC-1
                    (NP
                    (NOUN+CASE_DEF_ACC استرداد)
                    (NP
                    (NOUN+CASE_DEF_GEN امتياز)
                    (NP
                    (NOUN+NSUFF_FEM_SG+CASE_DEF_GEN شركة)
                    (NP
                    (NOUN+CASE_DEF_GEN كهرباء)
                    (NP
                    (NOUN_PROP+CASE_INDEF_GEN بيروت))))))
                    (NP-TMP
                    (NOUN+CASE_DEF_ACC عام)
                    (NP
                    (NOUN_NUM 1954))))
                    (VP
                    (PV+PVSUFF_SUBJ:3MS استوجب)
                    (NP-SBJ
                    (-NONE- *T*-1))
                    (NP-OBJ
                    (NP
                    (NP
                    (NOUN+CASE_INDEF_ACC نضالا))
                </parse>
                <arg f="" g="We" n="0">-NONE- *</arg>
                <arg f="" g="To mention here, but not limited to, that reclaiming the concession of electricity in Beirut in 1954 required a struggle" n="1">ان نذكر  هنا , على سبيل المثال لا الحصر,  بان استرداد امتياز شركة كهرباء بيروت عام 1954 استوجب نضالا</arg>
            </example>
        </frame>
    </frameset>
</verb>
