<!DOCTYPE verb SYSTEM "verb.dtd">
<verb>
    <id>OaqoEad</id>
    <frameset cdef="" edef="cripple" id="01">
        <role argnum="0" argrole="crippling agent"/>
        <role argnum="1" argrole="entity being crippled"/>
        <role argnum="2" argrole="action affected"/>
        <frame>
            <example>
                <parse>
                    (S
                    (S
                    (CONJ و)
                    (VP
                    (PRT
                    (NEG_PART لن))
                    (IV3MS+IV+IVSUFF_MOOD:S يصدق)
                    (NP-SBJ
                    (NOUN+CASE_INDEF_NOM احد))
                    (SBAR
                    (SUB_CONJ ان)
                    (S
                    (NP-PRD
                    (NP
                    (DET+NOUN+CASE_DEF_ACC المرض))
                    (NP
                    (PRON_3MS هو)))
                    (SBAR-SBJ
                    (WHNP-1
                    (REL_PRON الذي))
                    (S
                    (VP
                    (PV+PVSUFF_SUBJ:3MS اقعد)
                    (NP-SBJ
                    (-NONE- *T*-1))
                    (NP-OBJ
                    (NOUN_PROP زاهية)
                    (NOUN_PROP قدورة))
                    (PP-CLR
                    (PP
                    (PREP عن)
                    (NP
                    (NP
                    (NOUN+NSUFF_FEM_SG+CASE_DEF_GEN حركت)
                    (NP
                    (POSS_PRON_3FS ها)))
                    (SBAR
                    (WHNP-2
                    (REL_PRON التي))
                    (S
                    (VP
                    (PRT
                    (NEG_PART لم))
                    (IV3FS+IV+IVSUFF_MOOD:J تكن)
                    (VP
                    (IV3FS+IV+IVSUFF_MOOD:I تهدأ)
                    (NP-SBJ
                    (-NONE- *T*-2))))))))
                    (PUNC ,)
                    (CONJ و)
                    (PP
                    (PREP عن)
                    (NP
                    (NP
                    (NOUN+CASE_DEF_GEN واجب)
                    (NP
                    (POSS_PRON_3FS ها)))
                    (SBAR
                    (WHNP-3
                    (REL_PRON الذي))
                    (S
                    (VP
                    (PRT
                    (NEG_PART ما))
                    (PV+PVSUFF_SUBJ:3FS تخلفت)
                    (NP-SBJ
                    (-NONE- *))
                    (PP-CLR
                    (PREP عن)
                    (NP
                    (NOUN+CASE_DEF_GEN ادائ)
                    (NP
                    (NP
                    (POSS_PRON_3MS ه))
                    (NP
                    (-NONE- *T*-3)))))
                    (NP-TMP
                    (NOUN+CASE_INDEF_ACC يوماً)))))))))))))))
                </parse>
                <arg f="" g="" n="0">-NONE- *T*-1</arg>
                <arg f="" g="Zahia Qadura" n="1">زاهية قدورة</arg>
                <arg f="" g="from her activity that never used to cease and from performing her duties which she has never failed to do, not even for a day." n="2">عن حركتها التي لم تكن تهدأ و عن واجبها الذي ما تخلفت عن إدائه يوما</arg>
            </example>
        </frame>
    </frameset>
    <frameset cdef="" edef="to seat" id="02">
        <role argnum="0" argrole="agent seating"/>
        <role argnum="1" argrole="entity being seated"/>
        <role argnum="2" argrole="the seat, place"/>
        <frame>
            <example>
                <parse>
                    أقعدني على عرش الحب
                </parse>
                <arg f="" g="" n="0">-NONE-*</arg>
                <arg f="" g="me" n="1">ني</arg>
                <arg f="" g="on the throne of love" n="2">على عرش الحب</arg>
            </example>
        </frame>
    </frameset>
</verb>
