<!DOCTYPE verb SYSTEM "verb.dtd">
<verb>
    <id>Salob</id>
    <comment/>
    <frameset cdef="" edef="crusifiction" id="01">
        <role argnum="0" argrole="entity crucifying"/>
        <frame>
            <mapping>
                <comment/>
            </mapping>
            <example>
                <parse>(PREP عدا)
                    (NP
                    (NP
                    (NP
                    (NOUN+CASE_DEF_GEN قتل)
                    (NP
                    (DET+NOUN+CASE_DEF_GEN الامراء)))
                    (PP
                    (PREP ل)
                    (NP
                    (DET+NOUN+CASE_DEF_GEN لامراء))))
                    (CONJ و)
                    (S-NOM
                    (VP
                    (NOUN.VN+CASE_DEF_GEN صلب)
                    (NP-SBJ
                    (NOUN_QUANT+CASE_DEF_GEN بعض)
                    (NP
                    (POSS_PRON_3MP هم)))
                    (NP-OBJ
                    (DET+NOUN_QUANT+CASE_DEF_ACC البعض)
                    (DET+ADJ+CASE_DEF_ACC الآخر))))
                    (PUNC ,)
                    (CONJ و)
                    (NP
                    (NOUN+CASE_DEF_GEN غير)
                    (NP
                    (NOUN_QUANT+CASE_DEF_GEN كل)
                    (NP
                    (NOUN+NSUFF_FEM_PL+CASE_DEF_GEN مؤامرات)
                    (NP
                    (NP
                    (NOUN+CASE_DEF_GEN نساء)
                    (NP
                    (DET+NOUN+CASE_DEF_GEN الاولاد)))
                    (CONJ و)
                    (NP
                    (NOUN+CASE_DEF_GEN اخوال)
                    (NP
                    (POSS_PRON_3MP هم))))))))
                    (PUNC .)))
                </parse>
                <comment/>
                <arg f="" g="some of them" n="0">بعضهم</arg>
                <arg f="" g="the others" n="1">البعض الآخر</arg>
            </example>
            <comment/>
        </frame>
        <comment/>
        <role argnum="1" argrole="entity crucified"/>
        <role argnum="2" argrole="on what/ location"/>
    </frameset>
</verb>
