<!DOCTYPE verb SYSTEM "verb.dtd">
<verb>
    <id>takAvaf</id>
    <comment/>
    <frameset cdef="" edef="thicken" id="01">
        <role argnum="1" argrole="thing becoming thicker"/>
        <frame>
            <mapping>
                <comment/>
            </mapping>
            <example>
                <parse>الضغط يتكاثف على الهند بشأن ألعاب الكومنويلث
                    
                    Arg 1: -None- -T-* (الضغط)
                    Arg goal:  على الهند
                    Arg Cau: بشأن ألعاب الكومنويلث
                </parse>
                <comment/>
            </example>
            <comment/>
        </frame>
        <comment/>
    </frameset>
</verb>
