<!DOCTYPE verb SYSTEM "verb.dtd">
<verb>
    <id>wADiH</id>
    <frameset cdef="" edef="clear / obvious / apparent / evident" id="01">
        <role argnum="1" argrole="clear / obvious / apparent / evident thing"/>
        <role argnum="2" argrole="in what? (marked by في)"/>
        <frame>
            <example>
                <parse>
                    (S
                    (CONJ ف)
                    (NP-SBJ
                    (DET+NOUN+CASE_DEF_NOM الموقف)
                    (DET+ADJ+CASE_DEF_NOM العربي))
                    (ADJP-PRD
                    (ADJP
                    (ADJ+CASE_INDEF_NOM واضح))
                    (PUNC ,)
                </parse>
                <arg f="" g="The Arab position" n="1">الموقف العربي</arg>
            </example>
        </frame>
    </frameset>
</verb>
