<!DOCTYPE verb SYSTEM "verb.dtd">
<verb>
    <id>wafiy~</id>
    <frameset cdef="" edef="loyal / faithful / truthful" id="01">
        <role argnum="1" argrole="loyal / faithful / truthful entity"/>
        <role argnum="2" argrole="for whom? (maeked by ل)"/>
        <frame>
            <example>
                <parse>
                    (S
                    (VP
                    (PSEUDO_VERB ان)
                    (NP-SBJ
                    (NOUN_QUANT+CASE_DEF_ACC كل)
                    (NP
                    (NP
                    (DEM_PRON_F هذه))
                    (NP
                    (DET+NOUN+NSUFF_FEM_PL+CASE_DEF_GEN المحطات))))
                    (NP-PRD
                    (NP
                    (NOUN+NSUFF_FEM_SG+CASE_INDEF_NOM ادلة))
                    (PP
                    (PREP على)
                    (SBAR
                    (SUB_CONJ ان)
                    (S
                    (NP-SBJ
                    (SBAR-NOM
                    (WHNP-2
                    (REL_PRON ما))
                    (S
                    (VP
                    (IV1P+IV+IVSUFF_MOOD:I نقول)
                    (NP-SBJ
                    (-NONE- *))
                    (NP-OBJ
                    (NP
                    (IVSUFF_DO:3MS ه))
                    (NP
                    (-NONE- *T*-2))))))
                    (NP
                    (PRON_3MS هو)))
                    (NP-PRD
                    (NOUN+CASE_DEF_NOM فعل)
                    (NP
                    (NP
                    (NOUN+CASE_INDEF_GEN ايمان))
                    (ADJP
                    (ADJ+CASE_INDEF_GEN مدعوم)
                    (PP
                    (PREP من)
                    (NP
                    (NP
                    (NOUN+NSUFF_FEM_SG+CASE_INDEF_GEN شريحة)
                    (ADJ+NSUFF_FEM_SG+CASE_INDEF_GEN واسعة))
                    (PP
                    (PP
                    (PREP من)
                    (NP
                    (NP
                    (DET+NOUN+NSUFF_MASC_PL_GEN الكتائبيين))
                    (SBAR
                    (WHNP-3
                    (REL_PRON الذين))
                    (S
                    (VP
                    (PV+PVSUFF_SUBJ:3MP ظلوا)
                    (NP-SBJ
                    (-NONE- *T*-3))
                    (ADJP-PRD
                    (ADJ+CASE_INDEF_ACC اوفياء)
                    (PP
                    (PREP ل)
                    (NP
                    (NOUN+CASE_DEF_GEN دم)
                    (NP
                    (NP
                    (DET+NOUN+CASE_DEF_GEN الشهداء))
                </parse>
                <arg f="" g="they" n="1">-NONE- *T*-3&amp;lt; الكتائبيين</arg>
                <arg f="" g="for the blood of martyrs" n="2">لدم الشهداء</arg>
            </example>
        </frame>
    </frameset>
</verb>
