<!DOCTYPE verb SYSTEM "verb.dtd">
<verb>
<id>{inomazaE</id>

<frameset cdef="" edef="to be teased or softened (usually cotton or  wool)" id="01" vncls="">
<role argnum="0" argrole="agent" vncls="" vntheta=""/>
<frame>
<mapping>

<comment/>
</mapping>
<example>
<parse>انمزع الصوف بالمشط</parse>

<arg f="" g="the wool" n="1">الصوف</arg>
<arg f="" g="with a comb" n="2">بالمشط</arg>
<comment/>
</example>

<comment/>
</frame>

<role argnum="1" argrole="cotton" vncls="" vntheta=""/>
<role argnum="2" argrole="instrument" vncls="" vntheta=""/>
<comment/>
</frameset>
<comment/>
</verb>
