<!DOCTYPE verb SYSTEM "verb.dtd">
<verb>
    <id>{inoqa$aE</id>
    <frameset cdef="" edef="to become clear (sky)" id="01">
        <role argnum="1" argrole="thing being cleared"/>
        <frame>
            <example>
                <parse>
                    (S
                    (S
                    (VP
                    (IV3FS+IV+IVSUFF_MOOD:I تطوف)
                    (NP-SBJ-1
                    (-NONE- *))
                    (NP-LOC
                    (NOUN+CASE_DEF_ACC فوق)
                    (NP
                    (POSS_PRON_3FS ها)))
                    (PP-MNR
                    (PREP في)
                    (NP
                    (NOUN رهافة)))
                    (PUNC ,)
                    (S-ADV
                    (VP
                    (IV3FS+IV+IVSUFF_MOOD:I تستخرج)
                    (NP-SBJ
                    (-NONE- *-1))
                    (PP
                    (PREP من)
                    (NP
                    (PRON_3FS ها)))
                    (NP-OBJ
                    (DET+NOUN+CASE_DEF_ACC النغم))
                    (NP-MNR
                    (NOUN+CASE_INDEF_ACC همساً))))))
                    (PUNC ,)
                    (CONJ و)
                    (S
                    (PP
                    (PREP في)
                    (NP
                    (NP
                    (DET+NOUN+CASE_DEF_GEN الاتصال)
                    (DET+ADJ+CASE_DEF_GEN العميق))
                    (PP
                    (PREP ب)
                    (NP
                    (PRON_3FS ها)))))
                    (VP
                    (IV3FS+IV+IVSUFF_MOOD:I تنقشع)
                    (NP-SBJ
                    (NOUN+NSUFF_FEM_SG+CASE_DEF_NOM نورانيت)
                    (NP
                    (POSS_PRON_3FS ها)))
                    (PP
                    (PREP في)
                    (NP
                    (NOUN+CASE_DEF_GEN وجدان)
                    (NP
                    (DET+NOUN+CASE_DEF_GEN السمع))))))
                    (PUNC .))
                </parse>
                <arg f="" g="it's prophetic vision" n="1">نورانيتها</arg>
                <arg f="loc" g="in the love of hearing" n="m">في وجدان السمع</arg>
            </example>
        </frame>
    </frameset>
</verb>
